README.md
setup.py
xbase_util/__init__.py
xbase_util/add_column_util.py
xbase_util/common_util.py
xbase_util/dangerous_util.py
xbase_util/es_db_util.py
xbase_util/esreq.py
xbase_util/geo_util.py
xbase_util/handle_features_util.py
xbase_util/packet_util.py
xbase_util/pcap_util.py
xbase_util/xbase_constant.py
xbase_util.egg-info/PKG-INFO
xbase_util.egg-info/SOURCES.txt
xbase_util.egg-info/dependency_links.txt
xbase_util.egg-info/not-zip-safe
xbase_util.egg-info/top_level.txt
xbase_util/../xbase_util_assets/changtingwaf.txt
xbase_util/../xbase_util_assets/new_pa.txt
xbase_util/../xbase_util_assets/pa.txt
xbase_util/db/__init__.py
xbase_util/db/initsqlite3.py
xbase_util/db/bean/ConfigBean.py
xbase_util/db/bean/CurrentConfigBean.py
xbase_util/db/bean/FlowBean.py
xbase_util/db/bean/TaskTemplateBean.py
xbase_util/db/bean/__init__.py
xbase_util/db/dao/ConfigDao.py
xbase_util/db/dao/CurrentConfigDao.py
xbase_util/db/dao/FlowDao.py
xbase_util/db/dao/TaskTemplateDao.py
xbase_util/db/dao/__init__.py