Metadata-Version: 2.4
Name: xbase_util
Version: 1.3.6
Summary: 网络安全基础工具
Home-page: https://gitee.com/jimonik/xbase_util.git
Author: xyt
Author-email: 2506564278@qq.com
License: <MIT License>
Dynamic: author
Dynamic: author-email
Dynamic: description
Dynamic: home-page
Dynamic: license
Dynamic: summary
